{
  "exemplos": [
    {
      "tipo": "Login bem-sucedido (Seguro)",
      "requisicao": {
        "evento": "login",
        "usuarioId": "usr-12345",
        "timestamp": "2025-04-28T21:58:00Z",
        "dispositivo": {
          "id": "device-abc-987",
          "ip": "177.23.45.10",
          "localizacao": {
            "pais": "BR",
            "cidade": "São Paulo"
          },
          "trustScore": 95,
          "descricao": "Chrome/Windows 10"
        },
        "biometriaFacial": {
          "match": true,
          "score": 0.98
        },
        "comportamento": {
          "inputRate": 1.2,
          "padraoMouse": "normal"
        }
      },
      "resposta": {
        "usuarioId": "usr-12345",
        "scoreRisco": 12,
        "categoria": "Seguro",
        "acaoRecomendada": "permitir"
      }
    },
    {
      "tipo": "Checkout com risco moderado (Revisar)",
      "requisicao": {
        "evento": "checkout",
        "usuarioId": "usr-67890",
        "timestamp": "2025-04-28T22:00:10Z",
        "dispositivo": {
          "id": "device-xyz-123",
          "ip": "201.55.32.101",
          "localizacao": {
            "pais": "BR",
            "regiao": "MG"
          },
          "trustScore": 30,
          "descricao": "Firefox/Ubuntu"
        },
        "biometriaFacial": {
          "match": false,
          "score": 0.0
        },
        "comportamento": {
          "inputRate": 0.5,
          "padraoMouse": "inconsistente",
          "historicoComprasSemelhantes": false
        }
      },
      "resposta": {
        "usuarioId": "usr-67890",
        "scoreRisco": 55,
        "categoria": "Revisar",
        "acaoRecomendada": "desafiar"
      }
    },
    {
      "tipo": "Login bloqueado automaticamente (Bloquear)",
      "requisicao": {
        "evento": "login",
        "usuarioId": "usr-54321",
        "timestamp": "2025-04-28T22:05:00Z",
        "dispositivo": {
          "id": "device-qwe-321",
          "ip": "23.150.19.8",
          "localizacao": {
            "pais": "US",
            "cidade": "New York"
          },
          "trustScore": 5,
          "descricao": "TorBrowser/Windows 10"
        },
        "biometriaFacial": {
          "match": false,
          "score": 0.0
        },
        "comportamento": {
          "inputRate": 0.0,
          "padraoMouse": "nenhum"
        }
      },
      "resposta": {
        "usuarioId": "usr-54321",
        "scoreRisco": 99,
        "categoria": "Bloquear",
        "acaoRecomendada": "bloquear",
        "motivos": [
          "IP_suspeito",
          "Tor"
        ]
      }
    }
  ]
}
